[
  {
    "value": "Scaring the Ghost Game: (Teacher Models):_key1",
    "component": "header",
    "variant": 2
  },
  {
    "value": "Scaring the Ghost Game: (Teacher Models):_key2",
    "component": "text"
  },
  {
    "value": "https://merakilearn.s3.ap-south-1.amazonaws.com/courseEditor/5a0e8f77-5941-4338-8c4a-f64b611e1341-image4.png",
    "component": "image",
    "alt": "Scaring the Ghost Game: (Teacher Models):_key3"
  },
  {
    "value": "Scaring the Ghost Game: (Teacher Models):_key4",
    "component": "text"
  },
  {
    "value": "https://merakilearn.s3.ap-south-1.amazonaws.com/courseEditor/ee2b8d3b-89b5-4ecd-abf2-4e232b698143-image.png",
    "component": "image",
    "alt": "Scaring the Ghost Game: (Teacher Models):_key5"
  },
  {
    "value": "Scaring the Ghost Game: (Teacher Models):_key6",
    "component": "text"
  },
  {
    "value": "https://merakilearn.s3.ap-south-1.amazonaws.com/courseEditor/d12860b8-f96b-4954-9781-2c00aae7a56a-image.png",
    "component": "image",
    "alt": "Scaring the Ghost Game: (Teacher Models):_key7"
  }
]