{
	"OutputOfCode_question1_key1": "ఉదాహరణ 1",
	"OutputOfCode_question1_key2": "కింది <span style=\"\">కోడ్</span> స్నిప్పెట్ యొక్క <span style=\"\">అవుట్‌పుట్</span> ఎలా ఉంటుంది?",
	"OutputOfCode_question1_key3": "<span style=\"\">కార్యక్రమం</span> :-",
	"OutputOfCode_question1_key4": "<span style=\"color: #eb9371; background-color: rgba(39, 41, 43, 0.83); box-shadow: 2px 2px 2px rgba(22, 9, 1, 0.6); border-radius: 2px; padding: 2px\">ఎంపికలు :-</span>",
	"OutputOfCode_question1_key5": "ఎ. <span style=\"\">కీలక</span> <span style=\"\">లోపం</span>",
	"OutputOfCode_question1_key6": "బి. 1",
	"OutputOfCode_question1_key7": "సి. {(2,3):2}",
	"OutputOfCode_question1_key8": "డి. {(1,2):1}",
	"OutputOfCode_question1_key9": "అవుట్‌పుట్:-",
	"OutputOfCode_question1_key10": "బి.1"
}